verify/__init__.py
verify/categorical.py
verify/datamodel.py
verify/metrics.py
verify/plot.py
PyForecastTools-1.1.1.dist-info/LICENSE.md
PyForecastTools-1.1.1.dist-info/METADATA
PyForecastTools-1.1.1.dist-info/WHEEL
PyForecastTools-1.1.1.dist-info/top_level.txt
PyForecastTools-1.1.1.dist-info/RECORD
